topsispg/__init__.py
topsispg/topsis.py
toposis_prakhar_101803365-1.2.1.dist-info/LICENSE.txt
toposis_prakhar_101803365-1.2.1.dist-info/METADATA
toposis_prakhar_101803365-1.2.1.dist-info/WHEEL
toposis_prakhar_101803365-1.2.1.dist-info/top_level.txt
toposis_prakhar_101803365-1.2.1.dist-info/RECORD
